captain/__init__.py
captain/agents/__init__.py
captain/agents/policy.py
captain/agents/state_monitor.py
captain/algorithms/__init__.py
captain/algorithms/empirical_env_setup.py
captain/algorithms/env_setup.py
captain/algorithms/geneticStrategies.py
captain/algorithms/marxan_setup.py
captain/algorithms/reinforce.py
captain/algorithms/runOptimizedPolicy.py
captain/algorithms/runPolicyEmpirical.py
captain/biodivinit/PhyloGenerator.py
captain/biodivinit/SimulatorInit.py
captain/biodivinit/__init__.py
captain/biodivsim/BioDivEnv.py
captain/biodivsim/CellClass.py
captain/biodivsim/ClimateGenerator.py
captain/biodivsim/DisturbanceGenerator.py
captain/biodivsim/EmpiricalBioDivEnv.py
captain/biodivsim/EmpiricalGrid.py
captain/biodivsim/SimGrid.py
captain/biodivsim/StateInitializer.py
captain/biodivsim/__init__.py
captain/plot/plot_env.py
captain_project-0.1.16.dist-info/METADATA
captain_project-0.1.16.dist-info/WHEEL
captain_project-0.1.16.dist-info/licenses/LICENSE.md
captain_project-0.1.16.dist-info/RECORD
