Metadata-Version: 2.1
Name: captain-project
Version: 0.1.16
Summary: Conservation Area Prioritization Through Artificial INtelligence
Project-URL: Home, https://www.captain-project.net
Project-URL: Source, https://github.com/captain-project/captain-project
Project-URL: Documentation, https://github.com/captain-project/notebooks
Author-email: Daniele Silvestro <captain.project.team@gmail.com>
Classifier: Operating System :: OS Independent
Classifier: Programming Language :: Python :: 3
Requires-Python: >=3.8
Requires-Dist: baltic~=0.1.6
Requires-Dist: dendropy~=4.5.2
Requires-Dist: gym~=0.21.0
Requires-Dist: matplotlib~=3.5.1
Requires-Dist: numba~=0.55.0
Requires-Dist: numpy~=1.21.0
Requires-Dist: pandas~=1.4.3
Requires-Dist: scipy~=1.7.3
Requires-Dist: seaborn~=0.11.2
